{"id":"CR_1_20250409205601","type":"list","period":"last","title":"Custom Report","owner":"1","generated":"2025-04-09 20:56:00","graphtype":"line","filter":"allhcp","note":"dDI\u003d","subcriteria":[],"criteria":[{"name":"ramq","iddata":"0","section":"1","value":"0","operator":"equal","display":"RAMQ","type":"none"},{"name":"chart","iddata":"0","section":"1","value":"0","operator":"equal","display":"Chart","type":"none"},{"name":"idcommunity","iddata":"0","section":"1","value":"4","operator":"equal","display":"Community","type":"select"}],"dataset":[{"idpatient":"4122","ramq":"KOOV73562919","id":"135","idcommunity":"Nemaska","chart":"1517"},{"idpatient":"2940","ramq":"JOLR39021618","id":"90","idcommunity":"Nemaska","chart":"171"},{"idpatient":"4145","ramq":"BLAJ75112414","id":"136","idcommunity":"Nemaska","chart":"0"},{"idpatient":"4268","ramq":"SWAG55042824","id":"141","idcommunity":"Nemaska","chart":"286"},{"idpatient":"9615","ramq":"MARM64610927","id":"212","idcommunity":"Nemaska","chart":"151"},{"idpatient":"3378","ramq":"NEEI81092011","id":"105","idcommunity":"Nemaska","chart":"0"},{"idpatient":"3335","ramq":"CHEJ76091210","id":"103","idcommunity":"Nemaska","chart":"39"},{"idpatient":"3876","ramq":"WAPV95552716","id":"126","idcommunity":"Nemaska","chart":"412"},{"idpatient":"4686","ramq":"NEEL65610418","id":"171","idcommunity":"Nemaska","chart":"411"},{"idpatient":"7975","ramq":"WAPC81622810","id":"188","idcommunity":"Nemaska","chart":"365"},{"idpatient":"7869","ramq":"GEOM82601513","id":"185","idcommunity":"Nemaska","chart":"339"},{"idpatient":"3060","ramq":"VISG91511611","id":"95","idcommunity":"Nemaska","chart":"841"},{"idpatient":"8207","ramq":"TANO82602011","id":"193","idcommunity":"Nemaska","chart":"321"},{"idpatient":"335","ramq":"TRAB74540613","id":"0","idcommunity":"Nemaska","chart":"1342"},{"idpatient":"10391","ramq":"WAPD93520710","id":"233","idcommunity":"Nemaska","chart":"0"},{"idpatient":"4357","ramq":"JOLS79570814","id":"147","idcommunity":"Nemaska","chart":"177"},{"idpatient":"1005","ramq":"TANL69621318","id":"17","idcommunity":"Nemaska","chart":"314"},{"idpatient":"4334","ramq":"PEPQ91612315","id":"144","idcommunity":"Nemaska","chart":"1588"},{"idpatient":"8058","ramq":"MOAN71621717","id":"191","idcommunity":"Nemaska","chart":"236"},{"idpatient":"3913","ramq":"WAPC85511418","id":"127","idcommunity":"Nemaska","chart":"370"},{"idpatient":"501","ramq":"DIXE57571314","id":"9","idcommunity":"Nemaska","chart":"300"},{"idpatient":"4543","ramq":"PAVP87561712","id":"155","idcommunity":"Nemaska","chart":"1509"},{"idpatient":"5725","ramq":"MOAS69591315","id":"175","idcommunity":"Nemaska","chart":"445"},{"idpatient":"10096","ramq":"MOAL68041011","id":"229","idcommunity":"Nemaska","chart":"227"},{"idpatient":"3747","ramq":"MOAM86610513","id":"121","idcommunity":"Nemaska","chart":"232"},{"idpatient":"3129","ramq":"NEEL46052816","id":"98","idcommunity":"Nemaska","chart":"253"},{"idpatient":"3461","ramq":"WAPB77532315","id":"107","idcommunity":"Nemaska","chart":"362"},{"idpatient":"7852","ramq":"VISH95603018","id":"182","idcommunity":"Nemaska","chart":"938"},{"idpatient":"3066","ramq":"COOD65622018","id":"96","idcommunity":"Nemaska","chart":"298"},{"idpatient":"3916","ramq":"TAND57082919","id":"128","idcommunity":"Nemaska","chart":"296"},{"idpatient":"1603","ramq":"RABB53600610","id":"25","idcommunity":"Nemaska","chart":"103"},{"idpatient":"2482","ramq":"JOLR76570715","id":"66","idcommunity":"Nemaska","chart":"169"},{"idpatient":"4603","ramq":"METS57060611","id":"162","idcommunity":"Nemaska","chart":"212"},{"idpatient":"9950","ramq":"BELM64541316","id":"224","idcommunity":"Nemaska","chart":"1584"},{"idpatient":"4563","ramq":"BOBO76010619","id":"158","idcommunity":"Nemaska","chart":"496"},{"idpatient":"3470","ramq":"MOOA79620316","id":"108","idcommunity":"Nemaska","chart":"805"},{"idpatient":"1930","ramq":"NEES54102520","id":"42","idcommunity":"Nemaska","chart":"260"},{"idpatient":"2594","ramq":"ORRK84522215","id":"77","idcommunity":"Nemaska","chart":"265"},{"idpatient":"9335","ramq":"THUS94512717","id":"203","idcommunity":"Nemaska","chart":"929"},{"idpatient":"4609","ramq":"JOLW47031815","id":"163","idcommunity":"Nemaska","chart":"185"},{"idpatient":"2571","ramq":"BRIA63090713","id":"75","idcommunity":"Nemaska","chart":"17"},{"idpatient":"5691","ramq":"WAPN68562418","id":"174","idcommunity":"Nemaska","chart":"422"},{"idpatient":"5737","ramq":"WAPJ85031216","id":"176","idcommunity":"Nemaska","chart":"405"},{"idpatient":"4612","ramq":"WAPN82592710","id":"164","idcommunity":"Nemaska","chart":"427"},{"idpatient":"1927","ramq":"JOLW55062619","id":"41","idcommunity":"Nemaska","chart":"183"},{"idpatient":"1970","ramq":"METP82550716","id":"48","idcommunity":"Nemaska","chart":"211"},{"idpatient":"3052","ramq":"NEEJ70572811","id":"93","idcommunity":"Nemaska","chart":"758"},{"idpatient":"4526","ramq":"WAWK87623111","id":"153","idcommunity":"Nemaska","chart":"0"},{"idpatient":"7855","ramq":"QUAD71051811","id":"183","idcommunity":"Nemaska","chart":"3177"},{"idpatient":"9375","ramq":"PAPD68511310","id":"206","idcommunity":"Nemaska","chart":"1512"},{"idpatient":"1652","ramq":"WAPG61022013","id":"35","idcommunity":"Nemaska","chart":"389"},{"idpatient":"2408","ramq":"WAPT61010313","id":"61","idcommunity":"Nemaska","chart":"449"},{"idpatient":"6799","ramq":"MATT98552812","id":"178","idcommunity":"Nemaska","chart":"1167"},{"idpatient":"2757","ramq":"CHAM56550118","id":"82","idcommunity":"Nemaska","chart":"168"},{"idpatient":"1426","ramq":"SWAS67012713","id":"23","idcommunity":"Nemaska","chart":"792"},{"idpatient":"1924","ramq":"MATR50052612","id":"38","idcommunity":"Nemaska","chart":"193"},{"idpatient":"4363","ramq":"TANN80511814","id":"148","idcommunity":"Nemaska","chart":"7771"},{"idpatient":"2110","ramq":"TANS62520311","id":"50","idcommunity":"Nemaska","chart":"448"},{"idpatient":"2179","ramq":"JIME47580512","id":"51","idcommunity":"Nemaska","chart":"122"},{"idpatient":"2302","ramq":"CHEE89521118","id":"56","idcommunity":"Nemaska","chart":"37"},{"idpatient":"3653","ramq":"BLAC79522218","id":"114","idcommunity":"Nemaska","chart":"5"},{"idpatient":"3776","ramq":"WAPA84522618","id":"122","idcommunity":"Nemaska","chart":"359"},{"idpatient":"8276","ramq":"CHEW83033112","id":"198","idcommunity":"Nemaska","chart":"48"},{"idpatient":"9919","ramq":"NEEN87070912","id":"220","idcommunity":"Nemaska","chart":"255"},{"idpatient":"9338","ramq":"SWAT87112412","id":"204","idcommunity":"Nemaska","chart":"291"},{"idpatient":"499","ramq":"TRAA74521418","id":"7","idcommunity":"Nemaska","chart":"336"},{"idpatient":"1604","ramq":"CHEE57573028","id":"26","idcommunity":"Nemaska","chart":"121"},{"idpatient":"9925","ramq":"JOLG93610412","id":"221","idcommunity":"Nemaska","chart":"153"},{"idpatient":"1953","ramq":"MATA60572813","id":"45","idcommunity":"Nemaska","chart":"29"},{"idpatient":"9802","ramq":"JOLR69020318","id":"218","idcommunity":"Nemaska","chart":"170"},{"idpatient":"8259","ramq":"JOLH51020211","id":"195","idcommunity":"Nemaska","chart":"128"},{"idpatient":"4329","ramq":"JOLK60031816","id":"143","idcommunity":"Nemaska","chart":"148"},{"idpatient":"4601","ramq":"WAPV85612217","id":"161","idcommunity":"Nemaska","chart":"453"},{"idpatient":"3413","ramq":"BRIM66522413","id":"106","idcommunity":"Nemaska","chart":"40"},{"idpatient":"9278","ramq":"JOLG86083012","id":"199","idcommunity":"Nemaska","chart":"126"},{"idpatient":"602","ramq":"TRAJ69030413","id":"11","idcommunity":"Nemaska","chart":"1219"},{"idpatient":"3138","ramq":"WAPA58111912","id":"99","idcommunity":"Nemaska","chart":"354"},{"idpatient":"496","ramq":"NEER53060213","id":"4","idcommunity":"Nemaska","chart":"257"},{"idpatient":"4326","ramq":"NEEA72090228","id":"142","idcommunity":"Nemaska","chart":"244"},{"idpatient":"3679","ramq":"CHEM67512114","id":"117","idcommunity":"Nemaska","chart":"41"},{"idpatient":"7847","ramq":"WAPN58602014","id":"181","idcommunity":"Nemaska","chart":"54"},{"idpatient":"4684","ramq":"NEER90571819","id":"170","idcommunity":"Nemaska","chart":"258"},{"idpatient":"3974","ramq":"TANL76590318","id":"130","idcommunity":"Nemaska","chart":"315"},{"idpatient":"3284","ramq":"METV83562516","id":"102","idcommunity":"Nemaska","chart":"214"},{"idpatient":"3682","ramq":"JOLJ95620613","id":"118","idcommunity":"Nemaska","chart":"489"},{"idpatient":"9341","ramq":"WAPR70520916","id":"205","idcommunity":"Nemaska","chart":"436"},{"idpatient":"2540","ramq":"BRIM93080314","id":"72","idcommunity":"Nemaska","chart":"24"},{"idpatient":"8159","ramq":"CHES86600313","id":"192","idcommunity":"Nemaska","chart":"15967"},{"idpatient":"502","ramq":"MOAN87032116","id":"10","idcommunity":"Nemaska","chart":"235"},{"idpatient":"2889","ramq":"WAPJ53070516","id":"85","idcommunity":"Nemaska","chart":"401"},{"idpatient":"874","ramq":"GEOD75622418","id":"13","idcommunity":"Nemaska","chart":"584"},{"idpatient":"3018","ramq":"JOLL60531710","id":"92","idcommunity":"Nemaska","chart":"68"},{"idpatient":"957","ramq":"WAPP51092114","id":"16","idcommunity":"Nemaska","chart":"430"},{"idpatient":"4681","ramq":"HOUR75051116","id":"169","idcommunity":"Nemaska","chart":"1142"},{"idpatient":"2995","ramq":"DIXM97601517","id":"91","idcommunity":"Nemaska","chart":"3424"},{"idpatient":"4575","ramq":"MOAB98552117","id":"159","idcommunity":"Nemaska","chart":"1166"},{"idpatient":"9985","ramq":"SWAM54042510","id":"228","idcommunity":"Nemaska","chart":"288"},{"idpatient":"3631","ramq":"COOC78560218","id":"113","idcommunity":"Nemaska","chart":"52"},{"idpatient":"4690","ramq":"JOLP83090115","id":"173","idcommunity":"Nemaska","chart":"163"},{"idpatient":"3811","ramq":"JOLJ75511318","id":"124","idcommunity":"Nemaska","chart":"147"},{"idpatient":"1275","ramq":"WAPA58600715","id":"21","idcommunity":"Nemaska","chart":"281"},{"idpatient":"9556","ramq":"WAPA42560317","id":"210","idcommunity":"Nemaska","chart":"101"},{"idpatient":"1653","ramq":"WAPJ56011618","id":"36","idcommunity":"Nemaska","chart":"396"},{"idpatient":"2440","ramq":"SWAM76102119","id":"64","idcommunity":"Nemaska","chart":"790"},{"idpatient":"4106","ramq":"RABS71602111","id":"134","idcommunity":"Nemaska","chart":"462"},{"idpatient":"9619","ramq":"WAPL85621315","id":"213","idcommunity":"Nemaska","chart":"412"},{"idpatient":"8042","ramq":"JOLG72531511","id":"189","idcommunity":"Nemaska","chart":"136"},{"idpatient":"2420","ramq":"MOAK83560318","id":"63","idcommunity":"Nemaska","chart":"225"},{"idpatient":"3817","ramq":"NEAL69572213","id":"125","idcommunity":"Nemaska","chart":"5514"},{"idpatient":"1610","ramq":"MOAP54122110","id":"29","idcommunity":"Nemaska","chart":"237"},{"idpatient":"2938","ramq":"RABR71571316","id":"89","idcommunity":"Nemaska","chart":"280"},{"idpatient":"9954","ramq":"MESS83612512","id":"226","idcommunity":"Nemaska","chart":"200"},{"idpatient":"8265","ramq":"COOG84082413","id":"196","idcommunity":"Nemaska","chart":"616"},{"idpatient":"9951","ramq":"ADAS76081912","id":"225","idcommunity":"Nemaska","chart":"1082"},{"idpatient":"4335","ramq":"LACS72542712","id":"145","idcommunity":"Nemaska","chart":"935"},{"idpatient":"1607","ramq":"JOLE45581217","id":"27","idcommunity":"Nemaska","chart":"190"},{"idpatient":"3983","ramq":"SAGR91610517","id":"131","idcommunity":"Nemaska","chart":"923"},{"idpatient":"1616","ramq":"TANE42622612","id":"32","idcommunity":"Nemaska","chart":"301"},{"idpatient":"2280","ramq":"CHEM73021318","id":"54","idcommunity":"Nemaska","chart":"42"},{"idpatient":"2326","ramq":"CHEC80600910","id":"58","idcommunity":"Nemaska","chart":"33"},{"idpatient":"9419","ramq":"CHEB50591516","id":"208","idcommunity":"Nemaska","chart":"1"},{"idpatient":"7879","ramq":"DIAK93591311","id":"186","idcommunity":"Nemaska","chart":"32629"},{"idpatient":"1613","ramq":"WAPY40552010","id":"31","idcommunity":"Nemaska","chart":"263"},{"idpatient":"1951","ramq":"MATH56530121","id":"44","idcommunity":"Nemaska","chart":"228"},{"idpatient":"2197","ramq":"GILE60070911","id":"53","idcommunity":"Nemaska","chart":"1908"},{"idpatient":"1241","ramq":"WAPP69612617","id":"20","idcommunity":"Nemaska","chart":"429"},{"idpatient":"1931","ramq":"WAPJ67622515","id":"43","idcommunity":"Nemaska","chart":"397"},{"idpatient":"2864","ramq":"JOLW84062015","id":"83","idcommunity":"Nemaska","chart":"184"},{"idpatient":"3597","ramq":"WAPB77571911","id":"111","idcommunity":"Nemaska","chart":"361"},{"idpatient":"2409","ramq":"MIAM65120314","id":"62","idcommunity":"Nemaska","chart":"1232"},{"idpatient":"7819","ramq":"WAPL67051410","id":"180","idcommunity":"Nemaska","chart":"410"},{"idpatient":"2927","ramq":"JOLW83033017","id":"88","idcommunity":"Nemaska","chart":"181"},{"idpatient":"7859","ramq":"JOLR79531514","id":"184","idcommunity":"Nemaska","chart":"173"},{"idpatient":"2904","ramq":"BLAB72520315","id":"87","idcommunity":"Nemaska","chart":"587"},{"idpatient":"3986","ramq":"WAPP84512718","id":"132","idcommunity":"Nemaska","chart":"431"},{"idpatient":"640","ramq":"PACE58580113","id":"12","idcommunity":"Nemaska","chart":"248"},{"idpatient":"1181","ramq":"NEEE60542712","id":"19","idcommunity":"Nemaska","chart":"204"},{"idpatient":"10126","ramq":"WAPJ81073115","id":"231","idcommunity":"Nemaska","chart":"835"},{"idpatient":"9625","ramq":"JOLP97591019","id":"214","idcommunity":"Nemaska","chart":"1158"},{"idpatient":"2595","ramq":"WAPC85580312","id":"78","idcommunity":"Nemaska","chart":"369"},{"idpatient":"1925","ramq":"MOAW49080213","id":"39","idcommunity":"Nemaska","chart":"240"},{"idpatient":"2011","ramq":"TANK53531213","id":"49","idcommunity":"Nemaska","chart":"252"},{"idpatient":"494","ramq":"JOLI48022410","id":"2","idcommunity":"Nemaska","chart":"132"},{"idpatient":"3059","ramq":"WESD79592112","id":"94","idcommunity":"Nemaska","chart":"761"},{"idpatient":"3746","ramq":"WAPS73062714","id":"120","idcommunity":"Nemaska","chart":"444"},{"idpatient":"2518","ramq":"NEER57522114","id":"70","idcommunity":"Nemaska","chart":"323"},{"idpatient":"4456","ramq":"JOLL77580711","id":"151","idcommunity":"Nemaska","chart":"152"},{"idpatient":"9949","ramq":"CHER69063013","id":"223","idcommunity":"Nemaska","chart":"43"},{"idpatient":"3102","ramq":"MOAR88562219","id":"97","idcommunity":"Nemaska","chart":"1686"},{"idpatient":"3792","ramq":"TANT78521711","id":"123","idcommunity":"Nemaska","chart":"326"},{"idpatient":"500","ramq":"STEK63602510","id":"8","idcommunity":"Nemaska","chart":"206"},{"idpatient":"4244","ramq":"GULD67052714","id":"138","idcommunity":"Nemaska","chart":"474"},{"idpatient":"4267","ramq":"METS56060611","id":"140","idcommunity":"Nemaska","chart":"0"},{"idpatient":"8266","ramq":"JOLJ75121910","id":"197","idcommunity":"Nemaska","chart":"142"},{"idpatient":"2558","ramq":"WAPJ83572614","id":"73","idcommunity":"Nemaska","chart":"399"},{"idpatient":"2727","ramq":"WAPH63101716","id":"80","idcommunity":"Nemaska","chart":"391"},{"idpatient":"497","ramq":"METL68580212","id":"5","idcommunity":"Nemaska","chart":"208"},{"idpatient":"9843","ramq":"COOE91512917","id":"219","idcommunity":"Nemaska","chart":"18194"},{"idpatient":"7885","ramq":"MATS94591318","id":"187","idcommunity":"Nemaska","chart":"495"},{"idpatient":"9282","ramq":"CHEB60562017","id":"200","idcommunity":"Nemaska","chart":"338"},{"idpatient":"4662","ramq":"NEEL76582210","id":"167","idcommunity":"Nemaska","chart":"254"},{"idpatient":"4370","ramq":"VISM96512114","id":"150","idcommunity":"Nemaska","chart":"490"},{"idpatient":"1622","ramq":"WAPW44101816","id":"33","idcommunity":"Nemaska","chart":"455"},{"idpatient":"2893","ramq":"BRIH41552617","id":"86","idcommunity":"Nemaska","chart":"344"},{"idpatient":"7802","ramq":"POUM63510218","id":"179","idcommunity":"Nemaska","chart":"416"},{"idpatient":"3666","ramq":"JIMT72070519","id":"115","idcommunity":"Nemaska","chart":"92"},{"idpatient":"9926","ramq":"SAMM92580312","id":"222","idcommunity":"Nemaska","chart":"1589"},{"idpatient":"1960","ramq":"NEEE74562511","id":"46","idcommunity":"Nemaska","chart":"247"},{"idpatient":"2309","ramq":"MOAD73550819","id":"57","idcommunity":"Nemaska","chart":"221"},{"idpatient":"9626","ramq":"WAPA48590415","id":"215","idcommunity":"Nemaska","chart":"97"},{"idpatient":"10390","ramq":"MATC48112119","id":"232","idcommunity":"Nemaska","chart":"0"},{"idpatient":"4548","ramq":"COWA95592416","id":"156","idcommunity":"Nemaska","chart":"1120"},{"idpatient":"1608","ramq":"SALL59590310","id":"28","idcommunity":"Nemaska","chart":"229"},{"idpatient":"1654","ramq":"CHED71560918","id":"37","idcommunity":"Nemaska","chart":"60"},{"idpatient":"2192","ramq":"TRAW65123119","id":"52","idcommunity":"Nemaska","chart":"351"},{"idpatient":"9331","ramq":"HERJ96622016","id":"202","idcommunity":"Nemaska","chart":"29854"},{"idpatient":"2461","ramq":"SWAE86582516","id":"65","idcommunity":"Nemaska","chart":"285"},{"idpatient":"1926","ramq":"BLAR69601111","id":"40","idcommunity":"Nemaska","chart":"1300"},{"idpatient":"9414","ramq":"NEEC58611517","id":"207","idcommunity":"Nemaska","chart":"195"},{"idpatient":"10124","ramq":"JOLW84090410","id":"230","idcommunity":"Nemaska","chart":"182"},{"idpatient":"2590","ramq":"WAPE78581413","id":"76","idcommunity":"Nemaska","chart":"382"},{"idpatient":"3672","ramq":"ICEJ90592314","id":"116","idcommunity":"Nemaska","chart":"932"},{"idpatient":"3609","ramq":"COOE56511516","id":"112","idcommunity":"Nemaska","chart":"383"},{"idpatient":"3217","ramq":"WAPA81032810","id":"100","idcommunity":"Nemaska","chart":"356"},{"idpatient":"3546","ramq":"MESJ79620115","id":"110","idcommunity":"Nemaska","chart":"199"},{"idpatient":"1276","ramq":"WABD65612419","id":"22","idcommunity":"Nemaska","chart":"579"},{"idpatient":"2358","ramq":"STEV84552714","id":"59","idcommunity":"Nemaska","chart":"1081"},{"idpatient":"9689","ramq":"SWAD79081119","id":"216","idcommunity":"Nemaska","chart":"283"},{"idpatient":"4339","ramq":"MOAJ89620215","id":"146","idcommunity":"Nemaska","chart":"224"},{"idpatient":"2378","ramq":"WAPA67610819","id":"60","idcommunity":"Nemaska","chart":"357"},{"idpatient":"9563","ramq":"SHEC75081710","id":"211","idcommunity":"Nemaska","chart":"1090"},{"idpatient":"8043","ramq":"NEEE64511421","id":"190","idcommunity":"Nemaska","chart":"247"},{"idpatient":"2504","ramq":"TANK48120413","id":"69","idcommunity":"Nemaska","chart":"313"},{"idpatient":"2524","ramq":"WABS77563016","id":"71","idcommunity":"Nemaska","chart":"605"},{"idpatient":"4688","ramq":"BLAK74073017","id":"172","idcommunity":"Nemaska","chart":"8"},{"idpatient":"3921","ramq":"BLAL63552511","id":"129","idcommunity":"Nemaska","chart":"857"},{"idpatient":"1963","ramq":"WAPS65042111","id":"47","idcommunity":"Nemaska","chart":"440"},{"idpatient":"1611","ramq":"JOLW46511119","id":"30","idcommunity":"Nemaska","chart":"241"},{"idpatient":"9311","ramq":"WAPP67550513","id":"201","idcommunity":"Nemaska","chart":"447"},{"idpatient":"3987","ramq":"WAPC95521119","id":"133","idcommunity":"Nemaska","chart":"480"},{"idpatient":"4528","ramq":"SWAP76081012","id":"154","idcommunity":"Nemaska","chart":"290"},{"idpatient":"2756","ramq":"BLAS82531515","id":"81","idcommunity":"Nemaska","chart":"10"},{"idpatient":"4245","ramq":"MATA56530117","id":"139","idcommunity":"Nemaska","chart":"0"},{"idpatient":"3704","ramq":"JOLE96581116","id":"119","idcommunity":"Nemaska","chart":"1484"},{"idpatient":"4368","ramq":"TANT98620712","id":"149","idcommunity":"Nemaska","chart":"1176"},{"idpatient":"5742","ramq":"COOC00532315","id":"177","idcommunity":"Nemaska","chart":"1195"},{"idpatient":"956","ramq":"TENH46541913","id":"15","idcommunity":"Nemaska","chart":"390"},{"idpatient":"2725","ramq":"CHEC92592115","id":"79","idcommunity":"Nemaska","chart":"34"},{"idpatient":"1597","ramq":"WAPA56572517","id":"24","idcommunity":"Nemaska","chart":"16"},{"idpatient":"495","ramq":"NEEN58562911","id":"3","idcommunity":"Nemaska","chart":"421"},{"idpatient":"936","ramq":"KITR69092917","id":"14","idcommunity":"Nemaska","chart":"729"},{"idpatient":"4557","ramq":"WAPG50022816","id":"157","idcommunity":"Nemaska","chart":"387"},{"idpatient":"2868","ramq":"MESJ77560518","id":"84","idcommunity":"Nemaska","chart":"198"},{"idpatient":"2496","ramq":"WAPJ71082610","id":"68","idcommunity":"Nemaska","chart":"404"},{"idpatient":"9775","ramq":"BLAT60030318","id":"217","idcommunity":"Nemaska","chart":"552"},{"idpatient":"4597","ramq":"DECS88041916","id":"160","idcommunity":"Nemaska","chart":"1072"},{"idpatient":"2287","ramq":"BRIE69560512","id":"55","idcommunity":"Nemaska","chart":"1116"},{"idpatient":"3369","ramq":"TRAM60551011","id":"104","idcommunity":"Nemaska","chart":"333"},{"idpatient":"3475","ramq":"VISB70612711","id":"109","idcommunity":"Nemaska","chart":"352"},{"idpatient":"4471","ramq":"TANP90572118","id":"152","idcommunity":"Nemaska","chart":"322"},{"idpatient":"492","ramq":"JOLC60541812","id":"1","idcommunity":"Nemaska","chart":"27"},{"idpatient":"2493","ramq":"CHEE61071212","id":"67","idcommunity":"Nemaska","chart":"3396"},{"idpatient":"1096","ramq":"WIED62560512","id":"18","idcommunity":"Nemaska","chart":"1091"},{"idpatient":"8235","ramq":"WAPR65102216","id":"194","idcommunity":"Nemaska","chart":"433"},{"idpatient":"2559","ramq":"RABA88590914","id":"74","idcommunity":"Nemaska","chart":"219"},{"idpatient":"9443","ramq":"MATE76120911","id":"209","idcommunity":"Nemaska","chart":"1764"},{"idpatient":"9961","ramq":"WAPE87102016","id":"227","idcommunity":"Nemaska","chart":"384"},{"idpatient":"498","ramq":"STED55581118","id":"6","idcommunity":"Nemaska","chart":"120"},{"idpatient":"4242","ramq":"BLAE54560314","id":"137","idcommunity":"Nemaska","chart":"438"},{"idpatient":"3223","ramq":"JOLM79522518","id":"101","idcommunity":"Nemaska","chart":"156"},{"idpatient":"4614","ramq":"JOLC93071712","id":"165","idcommunity":"Nemaska","chart":"246"},{"idpatient":"4657","ramq":"WAPN76121717","id":"166","idcommunity":"Nemaska","chart":"420"},{"idpatient":"4677","ramq":"RABD74040612","id":"168","idcommunity":"Nemaska","chart":"585"},{"idpatient":"1623","ramq":"BLAR54560314","id":"34","idcommunity":"Nemaska","chart":"438"}],"header":{"ramq":"RAMQ","idcommunity":"Community","chart":"Chart"}}